quickdev/__init__.py
quickdev/qdstart.py
quickdev-0.0.1.dist-info/LICENSE
quickdev-0.0.1.dist-info/METADATA
quickdev-0.0.1.dist-info/WHEEL
quickdev-0.0.1.dist-info/top_level.txt
quickdev-0.0.1.dist-info/RECORD
